reportpl/__init__.py
reportpl/__main__.py
reportpl/api/__init__.py
reportpl/api/app.py
reportpl/api/config.py
reportpl/api/database/__init__.py
reportpl/api/database/db_class.py
reportpl/api/database/models.py
reportpl/api/database/repo.py
reportpl/api/helpers.py
reportpl/api/static/front/css/main.6457d1bc.css
reportpl/api/static/front/css/main.6457d1bc.css.map
reportpl/api/static/front/filenames.json
reportpl/api/static/front/js/787.f028a459.chunk.js
reportpl/api/static/front/js/787.f028a459.chunk.js.map
reportpl/api/static/front/js/main.9b4b1982.js
reportpl/api/static/front/js/main.9b4b1982.js.LICENSE.txt
reportpl/api/static/front/js/main.9b4b1982.js.map
reportpl/api/templates/base.html
reportpl/api/test.http
reportpl/base_web_form.py
reportpl/config.py
reportpl/converters.py
reportpl/copy_spa.py
reportpl/doc_handler/__init__.py
reportpl/doc_handler/docx_handler.py
reportpl/doc_handler/filters.py
reportpl/doc_handler/helpers_filters.py
reportpl/doc_handler/jenv.py
reportpl/doc_handler/jinja_env_functions.py
reportpl/doc_handler/subdoc/__init__.py
reportpl/doc_handler/subdoc/subdoc.py
reportpl/doc_handler/subdoc_html/__init__.py
reportpl/doc_handler/subdoc_html/elment_parses/__init__.py
reportpl/doc_handler/subdoc_html/elment_parses/heading.py
reportpl/doc_handler/subdoc_html/elment_parses/image.py
reportpl/doc_handler/subdoc_html/elment_parses/paragraph.py
reportpl/doc_handler/subdoc_html/elment_parses/run.py
reportpl/doc_handler/subdoc_html/elment_parses/utils.py
reportpl/doc_handler/subdoc_html/subdoc_html.py
reportpl/helpers.py
reportpl/html_render/__init__.py
reportpl/model_info.py
reportpl/models_example/__init__.py
reportpl/models_example/celular_sinf/__init__.py
reportpl/models_example/celular_sinf/filters/__init__.py
reportpl/models_example/celular_sinf/functions/__init__.py
reportpl/models_example/celular_sinf/init_dir.py
reportpl/models_example/celular_sinf/initial_feeder.py
reportpl/models_example/celular_sinf/lists/opcoes_midias.json
reportpl-0.3.0.dist-info/WHEEL
reportpl-0.3.0.dist-info/METADATA
reportpl-0.3.0.dist-info/RECORD
