Metadata-Version: 2.1
Name: reportpl
Version: 0.3.0
Summary: 
Author: renatormc
Author-email: renatomartinsrmc@gmail.com
Requires-Python: >=3.10,<4.0
Classifier: Programming Language :: Python :: 3
Classifier: Programming Language :: Python :: 3.10
Classifier: Programming Language :: Python :: 3.11
Requires-Dist: Flask (>=2.1.2,<3.0.0)
Requires-Dist: Markdown (>=3.3.7,<4.0.0)
Requires-Dist: Pillow (>=9.1.0,<10.0.0)
Requires-Dist: SQLAlchemy (>=1.4.36,<2.0.0)
Requires-Dist: beautifulsoup4
Requires-Dist: docxtpl (>=0.16.0,<0.17.0)
Requires-Dist: pdfminer-six (>=20221105,<20221106)
Requires-Dist: stringcase (>=1.2.0,<2.0.0)
